{
  "id": 1538411,
  "title": "Prisoners in Space",
  "tagline": "",
  "overview": "",
  "release_date": "2025-09-01",
  "runtime": 102,
  "vote_average": 0.0,
  "vote_count": 0,
  "genres": [
    "фантастика",
    "фэнтези",
    "боевик",
    "приключения",
    "триллер"
  ],
  "original_language": "en",
  "spoken_languages": [
    "English"
  ],
  "production_countries": [
    "GB"
  ],
  "poster_url": "https://image.tmdb.org/t/p/w500/25K8FezlGVIlufV1sF01yGsnKQ3.jpg",
  "backdrop_url": "https://image.tmdb.org/t/p/w780/3R2ieULS74jCnnhUTfnQavPNoiq.jpg",
  "tmdb_url": "https://www.themoviedb.org/movie/1538411",
  "trailer": {
    "key": "oyXEes8gCHI",
    "name": "Space: 1999 Prisoners in Space trailer - Super Space Theatre #space1999 #scifi #retro",
    "type": "Trailer"
  },
  "fetched_at_utc": "2025-09-01T01:08:29.147999+00:00",
  "notice": "This product uses the TMDB API but is not endorsed by TMDB."
}