{
  "id": 1538790,
  "title": "Internet Dreams",
  "tagline": "",
  "overview": "",
  "release_date": "2025-09-01",
  "runtime": 8,
  "vote_average": 0.0,
  "vote_count": 0,
  "genres": [],
  "original_language": "en",
  "spoken_languages": [],
  "production_countries": [],
  "poster_url": "https://image.tmdb.org/t/p/w500/1PVXe9y0x43bXcL604PmAGRBGSy.jpg",
  "backdrop_url": "https://image.tmdb.org/t/p/w780/sySC7rXvnU8VWfmrHsjTmYk9Kef.jpg",
  "tmdb_url": "https://www.themoviedb.org/movie/1538790",
  "trailer": null,
  "fetched_at_utc": "2025-09-01T01:08:28.411519+00:00",
  "notice": "This product uses the TMDB API but is not endorsed by TMDB."
}