{
  "id": 1559881,
  "title": "Crownless Queen of the Garden",
  "tagline": "",
  "overview": "",
  "release_date": "2025-10-10",
  "runtime": 20,
  "vote_average": 0.0,
  "vote_count": 0,
  "genres": [],
  "original_language": "he",
  "spoken_languages": [
    "Arabic",
    "Hebrew"
  ],
  "production_countries": [],
  "poster_url": "https://image.tmdb.org/t/p/w500/lFATzy5Y4pfZE1bt3Q3eKvDvyTx.jpg",
  "backdrop_url": null,
  "tmdb_url": "https://www.themoviedb.org/movie/1559881",
  "trailer": null,
  "fetched_at_utc": "2025-10-10T00:56:55.414857+00:00",
  "notice": "This product uses the TMDB API but is not endorsed by TMDB."
}