{
  "id": 1565961,
  "title": "Sin derecho a denunciar (Cooperativa El Bosque)",
  "tagline": "",
  "overview": "",
  "release_date": "2025-10-21",
  "runtime": 0,
  "vote_average": 0.0,
  "vote_count": 0,
  "genres": [
    "документальный"
  ],
  "original_language": "es",
  "spoken_languages": [
    "Spanish"
  ],
  "production_countries": [
    "SV"
  ],
  "poster_url": "https://image.tmdb.org/t/p/w500/qn5VoEjy5E6WYOBrCZv0MYy9fhh.jpg",
  "backdrop_url": "https://image.tmdb.org/t/p/w780/2dybebycQwdQBYETw8dzo4LbDe7.jpg",
  "tmdb_url": "https://www.themoviedb.org/movie/1565961",
  "trailer": null,
  "fetched_at_utc": "2025-10-21T06:19:31.724263+00:00",
  "notice": "This product uses the TMDB API but is not endorsed by TMDB."
}