{
  "id": 1593593,
  "title": "The Obsessive Shadow",
  "tagline": "",
  "overview": "",
  "release_date": "2025-12-05",
  "runtime": 12,
  "vote_average": 0.0,
  "vote_count": 0,
  "genres": [
    "ужасы",
    "триллер",
    "боевик"
  ],
  "original_language": "en",
  "spoken_languages": [
    "English"
  ],
  "production_countries": [
    "US"
  ],
  "poster_url": "https://image.tmdb.org/t/p/w500/jz5ZfAwdScuhMWh9vR4ySgb1eOP.jpg",
  "backdrop_url": "https://image.tmdb.org/t/p/w780/lxC7S969mq9gjOMMXu0BR5JqH8M.jpg",
  "tmdb_url": "https://www.themoviedb.org/movie/1593593",
  "trailer": null,
  "fetched_at_utc": "2025-12-05T18:17:41.867798+00:00",
  "notice": "This product uses the TMDB API but is not endorsed by TMDB."
}