{
  "id": 1596936,
  "title": "Tunico: Rir Não é o Suficiente",
  "tagline": "",
  "overview": "",
  "release_date": "2025-12-22",
  "runtime": 9,
  "vote_average": 0.0,
  "vote_count": 0,
  "genres": [
    "комедия",
    "документальный"
  ],
  "original_language": "pt",
  "spoken_languages": [
    "Portuguese"
  ],
  "production_countries": [],
  "poster_url": "https://image.tmdb.org/t/p/w500/zWkYdbfwoPo6TC4Rq90tkis9ZlS.jpg",
  "backdrop_url": "https://image.tmdb.org/t/p/w780/4Yggw3drhq4YcNfhiMrod5Us2GA.jpg",
  "tmdb_url": "https://www.themoviedb.org/movie/1596936",
  "trailer": null,
  "fetched_at_utc": "2025-12-22T01:07:55.218849+00:00",
  "notice": "This product uses the TMDB API but is not endorsed by TMDB."
}