{
  "id": 1605361,
  "title": "THE BIRTH OF A CANORUS.",
  "tagline": "",
  "overview": "",
  "release_date": "2025-12-29",
  "runtime": 17,
  "vote_average": 0.0,
  "vote_count": 0,
  "genres": [],
  "original_language": "en",
  "spoken_languages": [
    "Hindi"
  ],
  "production_countries": [
    "IN"
  ],
  "poster_url": "https://image.tmdb.org/t/p/w500/kzJOiOygissqIVKF9fGCvGwkpXr.jpg",
  "backdrop_url": "https://image.tmdb.org/t/p/w780/sbgEItFjzhV5Tev4veesdb7aces.jpg",
  "tmdb_url": "https://www.themoviedb.org/movie/1605361",
  "trailer": null,
  "fetched_at_utc": "2025-12-29T06:24:06.187189+00:00",
  "notice": "This product uses the TMDB API but is not endorsed by TMDB."
}