{
  "id": 1605735,
  "title": "Special Agent Tak: The Return",
  "tagline": "",
  "overview": "",
  "release_date": "2026-01-05",
  "runtime": 21,
  "vote_average": 0.0,
  "vote_count": 0,
  "genres": [
    "криминал",
    "боевик"
  ],
  "original_language": "en",
  "spoken_languages": [
    "English"
  ],
  "production_countries": [],
  "poster_url": "https://image.tmdb.org/t/p/w500/57y8uNuKDaxcXUvplbATVSP9qmY.jpg",
  "backdrop_url": "https://image.tmdb.org/t/p/w780/dmN7eHhmfRX7gF5nVrMmME9HuG0.jpg",
  "tmdb_url": "https://www.themoviedb.org/movie/1605735",
  "trailer": null,
  "fetched_at_utc": "2026-01-05T01:12:24.655326+00:00",
  "notice": "This product uses the TMDB API but is not endorsed by TMDB."
}