{
  "id": 1608415,
  "title": "Jeroen Verdick: Klein Gevaarlijk Afval",
  "tagline": "",
  "overview": "",
  "release_date": "2026-01-19",
  "runtime": 0,
  "vote_average": 0.0,
  "vote_count": 0,
  "genres": [
    "комедия"
  ],
  "original_language": "nl",
  "spoken_languages": [
    "Dutch"
  ],
  "production_countries": [
    "BE"
  ],
  "poster_url": "https://image.tmdb.org/t/p/w500/trqNdUmo7qm3iKSWGga4ukpBL2F.jpg",
  "backdrop_url": "https://image.tmdb.org/t/p/w780/qCG93MG6DEhdwNhrZQWy9iKFyTr.jpg",
  "tmdb_url": "https://www.themoviedb.org/movie/1608415",
  "trailer": null,
  "fetched_at_utc": "2026-01-19T12:31:56.554497+00:00",
  "notice": "This product uses the TMDB API but is not endorsed by TMDB."
}