{
  "id": 1614844,
  "title": "Tusker: Brotherhood of Elephants",
  "tagline": "",
  "overview": "",
  "release_date": "2026-01-14",
  "runtime": 56,
  "vote_average": 0.0,
  "vote_count": 0,
  "genres": [
    "документальный"
  ],
  "original_language": "en",
  "spoken_languages": [],
  "production_countries": [],
  "poster_url": "https://image.tmdb.org/t/p/w500/2IHzMNrdltlgLj6xtO33B8UdBRF.jpg",
  "backdrop_url": null,
  "tmdb_url": "https://www.themoviedb.org/movie/1614844",
  "trailer": null,
  "fetched_at_utc": "2026-01-14T01:09:06.519217+00:00",
  "notice": "This product uses the TMDB API but is not endorsed by TMDB."
}