{
  "id": 1618518,
  "title": "STARDOM 15th ANNIVERSARY STARDOM AWARD 2025 in TAKADANOBABA DAY2 〜試合〜",
  "tagline": "",
  "overview": "",
  "release_date": "2026-01-25",
  "runtime": 180,
  "vote_average": 0.0,
  "vote_count": 0,
  "genres": [
    "боевик",
    "драма"
  ],
  "original_language": "ja",
  "spoken_languages": [
    "Japanese"
  ],
  "production_countries": [
    "JP"
  ],
  "poster_url": "https://image.tmdb.org/t/p/w500/8VdEOmYaSrioJNTE1JxeicnJQOi.jpg",
  "backdrop_url": "https://image.tmdb.org/t/p/w780/yMnLOsF7QmrBFhQ6y3CT29mj4r0.jpg",
  "tmdb_url": "https://www.themoviedb.org/movie/1618518",
  "trailer": null,
  "fetched_at_utc": "2026-01-25T01:14:17.637973+00:00",
  "notice": "This product uses the TMDB API but is not endorsed by TMDB."
}