{
  "fetched_at_utc": "2025-10-22T18:19:44.711285+00:00",
  "region": null,
  "days_back": 30,
  "count": 10,
  "items": [
    {
      "id": 1566858,
      "title": "Ya no sé ni lo que digo",
      "release_date": "2025-10-22",
      "vote_average": 0.0,
      "poster_url": "https://image.tmdb.org/t/p/w500/qay9yKCrdPCYesD5hDypqqXSswL.jpg",
      "genres": [
        "комедия"
      ]
    },
    {
      "id": 1566786,
      "title": "Beat It",
      "release_date": "2025-10-22",
      "vote_average": 0.0,
      "poster_url": null,
      "genres": []
    },
    {
      "id": 1566784,
      "title": "Doll Love",
      "release_date": "2025-10-22",
      "vote_average": 0.0,
      "poster_url": null,
      "genres": []
    },
    {
      "id": 1566781,
      "title": "Sanguine",
      "release_date": "2025-10-22",
      "vote_average": 0.0,
      "poster_url": null,
      "genres": []
    },
    {
      "id": 1566779,
      "title": "Baiestorf Apresenta O Monstro Legume do Espaço 30 Anos",
      "release_date": "2025-10-22",
      "vote_average": 0.0,
      "poster_url": "https://image.tmdb.org/t/p/w500/wrSf4e8haefhmEAQAtPA33VyoBi.jpg",
      "genres": [
        "документальный"
      ]
    },
    {
      "id": 1566777,
      "title": "Mouth Pleasure",
      "release_date": "2025-10-22",
      "vote_average": 0.0,
      "poster_url": null,
      "genres": []
    },
    {
      "id": 1566776,
      "title": "Azimuth",
      "release_date": "2025-10-22",
      "vote_average": 0.0,
      "poster_url": "https://image.tmdb.org/t/p/w500/sw7U1U930k6MeKBhty2hafNPikz.jpg",
      "genres": []
    },
    {
      "id": 1566775,
      "title": "La Bonne Éducation (The Good Education)",
      "release_date": "2025-10-22",
      "vote_average": 0.0,
      "poster_url": null,
      "genres": []
    },
    {
      "id": 1566772,
      "title": "Alien Invade Me",
      "release_date": "2025-10-22",
      "vote_average": 0.0,
      "poster_url": null,
      "genres": []
    },
    {
      "id": 1566766,
      "title": "Autoerotic Centesis",
      "release_date": "2025-10-22",
      "vote_average": 0.0,
      "poster_url": null,
      "genres": []
    }
  ],
  "source": "TMDB",
  "notice": "This product uses the TMDB API but is not endorsed by TMDB."
}