{
  "fetched_at_utc": "2025-11-05T12:26:15.942525+00:00",
  "region": null,
  "days_back": 30,
  "count": 10,
  "items": [
    {
      "id": 1575059,
      "title": "Roland Emmerich - Weltenzerstörer, Weltenerbauer",
      "release_date": "2025-11-05",
      "vote_average": 0.0,
      "poster_url": "https://image.tmdb.org/t/p/w500/gyzm5VmKhBu32nfxerBNJkyaKMm.jpg",
      "genres": []
    },
    {
      "id": 1575002,
      "title": "Jangan Ambil Bonekaku..!! 3",
      "release_date": "2025-11-05",
      "vote_average": 0.0,
      "poster_url": "https://image.tmdb.org/t/p/w500/bNVdewNz4KNGctJkqwsgMBYThf5.jpg",
      "genres": [
        "криминал",
        "драма"
      ]
    },
    {
      "id": 1574995,
      "title": "Prisczilla",
      "release_date": "2025-11-05",
      "vote_average": 0.0,
      "poster_url": "https://image.tmdb.org/t/p/w500/yCO5tw6Xf97Fdq0JL2qCvSLGJFf.jpg",
      "genres": [
        "триллер",
        "комедия",
        "фантастика"
      ]
    },
    {
      "id": 1574908,
      "title": "هفت پیکر",
      "release_date": "2025-11-05",
      "vote_average": 0.0,
      "poster_url": "https://image.tmdb.org/t/p/w500/pounwU8OlutLYB1q1V8MwenBXwu.jpg",
      "genres": []
    },
    {
      "id": 1574810,
      "title": "Zaragoza, pionera del cine",
      "release_date": "2025-11-05",
      "vote_average": 0.0,
      "poster_url": "https://image.tmdb.org/t/p/w500/enHQ0zD5dXIwqyOkeFEApWChBBk.jpg",
      "genres": [
        "документальный"
      ]
    },
    {
      "id": 1574775,
      "title": "کشیدن نخ‌ها",
      "release_date": "2025-11-05",
      "vote_average": 0.0,
      "poster_url": null,
      "genres": []
    },
    {
      "id": 1574718,
      "title": "Bigay hilig: Sexual Fetish",
      "release_date": "2025-11-05",
      "vote_average": 8.0,
      "poster_url": "https://image.tmdb.org/t/p/w500/cZ53ujfSc8duZcheemIKsC2Zpf9.jpg",
      "genres": [
        "драма"
      ]
    },
    {
      "id": 1574674,
      "title": "Ηλέκτρα7",
      "release_date": "2025-11-05",
      "vote_average": 0.0,
      "poster_url": null,
      "genres": []
    },
    {
      "id": 1574158,
      "title": "The Drawer",
      "release_date": "2025-11-05",
      "vote_average": 10.0,
      "poster_url": "https://image.tmdb.org/t/p/w500/cBoSyLtFglRkpwmwWatndZs3FFC.jpg",
      "genres": []
    },
    {
      "id": 1574125,
      "title": "Inevitable Nostalgia",
      "release_date": "2025-11-05",
      "vote_average": 0.0,
      "poster_url": "https://image.tmdb.org/t/p/w500/4rxrw6xn7SaHa6m9GsfVAke5CRC.jpg",
      "genres": [
        "драма",
        "ужасы"
      ]
    }
  ],
  "source": "TMDB",
  "notice": "This product uses the TMDB API but is not endorsed by TMDB."
}