{
  "fetched_at_utc": "2025-11-12T06:20:10.905456+00:00",
  "region": null,
  "days_back": 30,
  "count": 10,
  "items": [
    {
      "id": 1579081,
      "title": "Basado en Pedas Reales",
      "release_date": "2025-11-12",
      "vote_average": 0.0,
      "poster_url": null,
      "genres": []
    },
    {
      "id": 1578867,
      "title": "Dangerous Rain",
      "release_date": "2025-11-12",
      "vote_average": 0.0,
      "poster_url": "https://image.tmdb.org/t/p/w500/4bwaWBtcgunA0P5it3qaffnSRMY.jpg",
      "genres": [
        "документальный"
      ]
    },
    {
      "id": 1578632,
      "title": "El Rey del Pescado Frito",
      "release_date": "2025-11-12",
      "vote_average": 0.0,
      "poster_url": null,
      "genres": []
    },
    {
      "id": 1578627,
      "title": "Stardom Goddesses of Stardom Tag League 2025 - Day 4",
      "release_date": "2025-11-12",
      "vote_average": 0.0,
      "poster_url": "https://image.tmdb.org/t/p/w500/7IDFYfESJDjA8u9WyUW3BSUy887.jpg",
      "genres": []
    },
    {
      "id": 1578617,
      "title": "Visita",
      "release_date": "2025-11-12",
      "vote_average": 0.0,
      "poster_url": null,
      "genres": []
    },
    {
      "id": 1578598,
      "title": "Nos vemos esta noche mi amor",
      "release_date": "2025-11-12",
      "vote_average": 0.0,
      "poster_url": "https://image.tmdb.org/t/p/w500/qS5mQJ3w2kbfmTBuLMwks9zAafx.jpg",
      "genres": [
        "ужасы"
      ]
    },
    {
      "id": 1578596,
      "title": "Historia de un pan: Pancho",
      "release_date": "2025-11-12",
      "vote_average": 0.0,
      "poster_url": null,
      "genres": []
    },
    {
      "id": 1578594,
      "title": "Delirio",
      "release_date": "2025-11-12",
      "vote_average": 0.0,
      "poster_url": null,
      "genres": []
    },
    {
      "id": 1578588,
      "title": "Los Audios de Abril",
      "release_date": "2025-11-12",
      "vote_average": 0.0,
      "poster_url": null,
      "genres": []
    },
    {
      "id": 1578587,
      "title": "Destino Equivocado",
      "release_date": "2025-11-12",
      "vote_average": 0.0,
      "poster_url": null,
      "genres": []
    }
  ],
  "source": "TMDB",
  "notice": "This product uses the TMDB API but is not endorsed by TMDB."
}